genericclient_aiohttp/__init__.py
genericclient_aiohttp/exceptions.py
genericclient_aiohttp/pagination.py
genericclient_aiohttp/routes.py
genericclient_aiohttp/utils.py
tests/__init__.py
tests/conftest.py
tests/test_auth.py
tests/test_client.py
tests/test_endpoint.py
tests/test_paginate.py
tests/test_resource.py
tests/test_routes.py
genericclient_aiohttp-1.4.2.dist-info/LICENSE
genericclient_aiohttp-1.4.2.dist-info/METADATA
genericclient_aiohttp-1.4.2.dist-info/WHEEL
genericclient_aiohttp-1.4.2.dist-info/top_level.txt
genericclient_aiohttp-1.4.2.dist-info/RECORD
