Metadata-Version: 2.1
Name: genericclient-aiohttp
Version: 1.4.2
Summary: UNKNOWN
Home-page: https://github.com/genericclient/genericclient-aiohttp
Author: Flavio Curella
Author-email: flavio.curella@gmail.com
License: UNKNOWN
Platform: UNKNOWN
Classifier: Development Status :: 4 - Beta
Classifier: Environment :: Web Environment
Classifier: Intended Audience :: Developers
Classifier: Operating System :: OS Independent
Classifier: Programming Language :: Python :: 3
Classifier: License :: OSI Approved :: MIT License
Requires-Dist: genericclient-base (==1.4.2)
Requires-Dist: aiodns (<1.2,>=1.1)
Requires-Dist: aiohttp (<3.6,>=3.5)
Requires-Dist: cchardet (<2.2,==2.1)
Requires-Dist: pyfailsafe (<0.3,>=0.2)
